grade_analysis/dictionary.py
grade_analysis/gradeAnalysisFunc.py
grade_analysis/gradeAnalysisGUI.py
grade_analysis/gradeAnalysisWidgets.py
gradeanalysistool-1.0.dist-info/METADATA
gradeanalysistool-1.0.dist-info/WHEEL
gradeanalysistool-1.0.dist-info/entry_points.txt
gradeanalysistool-1.0.dist-info/top_level.txt
gradeanalysistool-1.0.dist-info/RECORD
