Metadata-Version: 2.2
Name: GradeAnalysisTool
Version: 1.0
Summary: A short description of your grading analysis tool.
Author-email: Mario Marku <mariom@fordham.edu>
License: MIT
